sawtooth_signing/__init__.py
sawtooth_signing/core.py
sawtooth_signing/secp256k1.py
sawtooth_signing-1.1.5.dist-info/DESCRIPTION.rst
sawtooth_signing-1.1.5.dist-info/METADATA
sawtooth_signing-1.1.5.dist-info/RECORD
sawtooth_signing-1.1.5.dist-info/WHEEL
sawtooth_signing-1.1.5.dist-info/metadata.json
sawtooth_signing-1.1.5.dist-info/top_level.txt
