Metadata-Version: 1.0
Name: sawtooth-signing
Version: 1.1.5
Summary: Sawtooth Signing Library
Home-page: https://github.com/hyperledger/sawtooth-core
Author: Hyperledger Sawtooth
Author-email: UNKNOWN
License: UNKNOWN
Platform: UNKNOWN
